sharq/__init__.py
sharq/exceptions.py
sharq/queue.py
sharq/utils.py
sharq/scripts/lua/dequeue.lua
sharq/scripts/lua/enqueue.lua
sharq/scripts/lua/finish.lua
sharq/scripts/lua/interval.lua
sharq/scripts/lua/metrics.lua
sharq/scripts/lua/requeue.lua
SharQ-1.0.0.dist-info/LICENSE.txt
SharQ-1.0.0.dist-info/METADATA
SharQ-1.0.0.dist-info/WHEEL
SharQ-1.0.0.dist-info/top_level.txt
SharQ-1.0.0.dist-info/RECORD
