Metadata-Version: 2.1
Name: SharQ
Version: 1.0.0
Summary: An API queueing system built at Plivo.
Home-page: https://github.com/plivo/sharq
Author: Plivo Team
Author-email: voice-team@plivo.com
License: The MIT License (MIT)
Platform: UNKNOWN
Classifier: Development Status :: 5 - Production/Stable
Classifier: Intended Audience :: Developers
Classifier: License :: OSI Approved :: MIT License
Classifier: Operating System :: OS Independent
Classifier: Programming Language :: Python
Classifier: Topic :: Software Development :: Libraries :: Python Modules
Requires-Python: >3.5
Requires-Dist: msgpack (==0.5.6)
Requires-Dist: redis-py-cluster (==2.0.0)
